blurhash/__init__.py
blurhash/blurhash.py
blurhash-1.1.4.dist-info/DESCRIPTION.rst
blurhash-1.1.4.dist-info/METADATA
blurhash-1.1.4.dist-info/RECORD
blurhash-1.1.4.dist-info/WHEEL
blurhash-1.1.4.dist-info/metadata.json
blurhash-1.1.4.dist-info/top_level.txt
